reactpy/__init__.py
reactpy/__main__.py
reactpy/_option.py
reactpy/_warnings.py
reactpy/config.py
reactpy/future.py
reactpy/html.py
reactpy/logging.py
reactpy/py.typed
reactpy/sample.py
reactpy/svg.py
reactpy/types.py
reactpy/utils.py
reactpy/widgets.py
reactpy/_console/__init__.py
reactpy/_console/ast_utils.py
reactpy/_console/rewrite_camel_case_props.py
reactpy/_console/rewrite_keys.py
reactpy/_static/__init__.py
reactpy/_static/app/__init__.py
reactpy/_static/app/dist/__init__.py
reactpy/_static/app/dist/index.html
reactpy/_static/app/dist/assets/__init__.py
reactpy/_static/app/dist/assets/index.a1f87a11.js
reactpy/_static/app/dist/assets/reactpy-logo.ico
reactpy/backend/__init__.py
reactpy/backend/_common.py
reactpy/backend/default.py
reactpy/backend/fastapi.py
reactpy/backend/flask.py
reactpy/backend/hooks.py
reactpy/backend/robyn.py
reactpy/backend/sanic.py
reactpy/backend/starlette.py
reactpy/backend/tornado.py
reactpy/backend/types.py
reactpy/backend/utils.py
reactpy/core/__init__.py
reactpy/core/_f_back.py
reactpy/core/_life_cycle_hook.py
reactpy/core/_thread_local.py
reactpy/core/component.py
reactpy/core/events.py
reactpy/core/hooks.py
reactpy/core/layout.py
reactpy/core/serve.py
reactpy/core/types.py
reactpy/core/vdom.py
reactpy/web/__init__.py
reactpy/web/module.py
reactpy/web/utils.py
reactpy/web/templates/react.js
rpysuite/.DS_Store
rpysuite/__init__.py
rpysuite/bundle.js
rpysuite/idea.css
rpysuite/tailwind.css
rpysuite/__pycache__/__init__.cpython-311.pyc
rpysuite/builder/__init__.py
rpysuite/builder/loader.py
rpysuite/builder/main.py
rpysuite/builder/__pycache__/__init__.cpython-311.pyc
rpysuite/builder/__pycache__/loader.cpython-311.pyc
rpysuite/builder/__pycache__/main.cpython-311.pyc
rpysuite/components/.DS_Store
rpysuite/components/__init__.py
rpysuite/components/echarts.py
rpysuite/components/icons.py
rpysuite/components/mantine.py
rpysuite/components/markdown.py
rpysuite/components/monaco.py
rpysuite/components/web.py
rpysuite-0.0.3.dist-info/LICENSE
rpysuite-0.0.3.dist-info/METADATA
rpysuite-0.0.3.dist-info/WHEEL
rpysuite-0.0.3.dist-info/top_level.txt
rpysuite-0.0.3.dist-info/RECORD
