Metadata-Version: 2.1
Name: rpysuite
Version: 0.0.3
Summary: Reactive user interfaces with pure Python
Home-page: 
Author: dameng
Author-email: Ryan Morshead <ryan.morshead@gmail.com>
License: MIT
Project-URL: Source, https://github.com/reactive-python/reactpy
Project-URL: Documentation, https://github.com/reactive-python/reactpy#readme
Project-URL: Issues, https://github.com/reactive-python/reactpy/discussions
Keywords: react,javascript,reactpy,component
Platform: Linux
Platform: Mac OS X
Platform: Windows
Classifier: Development Status :: 4 - Beta
Classifier: Programming Language :: Python
Classifier: Programming Language :: Python :: 3.9
Classifier: Programming Language :: Python :: 3.10
Classifier: Programming Language :: Python :: 3.11
Classifier: Programming Language :: Python :: Implementation :: CPython
Classifier: Programming Language :: Python :: Implementation :: PyPy
Requires-Python: >=3.7
License-File: LICENSE
Requires-Dist: exceptiongroup >=1.0
Requires-Dist: typing-extensions >=3.10
Requires-Dist: mypy-extensions >=0.4.3
Requires-Dist: anyio >=3
Requires-Dist: jsonpatch >=1.32
Requires-Dist: fastjsonschema >=2.14.5
Requires-Dist: requests >=2
Requires-Dist: colorlog >=6
Requires-Dist: asgiref >=3
Requires-Dist: lxml >=4
Provides-Extra: all
Requires-Dist: reactpy[fastapi,flask,sanic,starlette,testing,tornado] ; extra == 'all'
Provides-Extra: fastapi
Requires-Dist: fastapi >=0.63.0 ; extra == 'fastapi'
Requires-Dist: uvicorn[standard] >=0.19.0 ; extra == 'fastapi'
Provides-Extra: flask
Requires-Dist: flask ; extra == 'flask'
Requires-Dist: markupsafe <2.1,>=1.1.1 ; extra == 'flask'
Requires-Dist: flask-cors ; extra == 'flask'
Requires-Dist: flask-sock ; extra == 'flask'
Provides-Extra: sanic
Requires-Dist: sanic >=21 ; extra == 'sanic'
Requires-Dist: sanic-cors ; extra == 'sanic'
Requires-Dist: tracerite >=1.1.1 ; extra == 'sanic'
Requires-Dist: setuptools ; extra == 'sanic'
Requires-Dist: uvicorn[standard] >=0.19.0 ; extra == 'sanic'
Provides-Extra: starlette
Requires-Dist: starlette >=0.13.6 ; extra == 'starlette'
Requires-Dist: uvicorn[standard] >=0.19.0 ; extra == 'starlette'
Provides-Extra: testing
Requires-Dist: playwright ; extra == 'testing'
Provides-Extra: tornado
Requires-Dist: tornado ; extra == 'tornado'
